AioPTTCrawler/__init__.py
AioPTTCrawler/crawler.py
AioPTTCrawler/ptt_crawler.py
AioPTTCrawler/ptt_data.py
AioPTTCrawler/model/__init__.py
AioPTTCrawler/model/article.py
AioPTTCrawler/model/author.py
AioPTTCrawler/model/comment.py
PttWebCrawler/__init__.py
PttWebCrawler/__main__.py
PttWebCrawler/crawler.py
AioPTTCrawler-0.0.12.dist-info/LICENSE
AioPTTCrawler-0.0.12.dist-info/METADATA
AioPTTCrawler-0.0.12.dist-info/WHEEL
AioPTTCrawler-0.0.12.dist-info/top_level.txt
AioPTTCrawler-0.0.12.dist-info/RECORD
