Metadata-Version: 2.1
Name: AioPTTCrawler
Version: 0.0.12
Summary: PTT crawler using asyncio
Home-page: https://github.com/DOUIF/aio-ptt-crawler
Author: DOUIF
Author-email: a15975345678@gmail.com
Classifier: Programming Language :: Python :: 3
Classifier: License :: OSI Approved :: MIT License
Classifier: Operating System :: OS Independent
Requires-Python: >=3.10
License-File: LICENSE
Requires-Dist: aiohttp (>=3.8.3)
Requires-Dist: lxml (>=4.9.1)
Requires-Dist: requests (>=2.28.1)
Requires-Dist: pandas (>=1.5.0)
